<?xml version="1.0" encoding="utf-8"?>
<hibernate-mapping schema="dbo" assembly="Domain" namespace="Domain" xmlns="urn:nhibernate-mapping-2.2">
  <class name="Modulo" table="Modulo">
    <id name="Id" type="Int32">
      <column name="Id" not-null="true" precision="10" scale="0" sql-type="int" />
      <generator class="identity" />
    </id>
    <property name="Icon" type="String">
      <column name="Icon" not-null="false" length="50" sql-type="nvarchar" />
    </property>
    <property name="NodoPadre" type="Int32">
      <column name="NodoPadre" not-null="false" precision="10" scale="0" sql-type="int" />
    </property>
    <property name="Nodo" type="Int32">
      <column name="Nodo" not-null="false" precision="10" scale="0" sql-type="int" />
    </property>
    <property name="Descripcion" type="String">
      <column name="Descripcion" not-null="false" sql-type="nvarchar" />
    </property>
    <property name="Url" type="String">
      <column name="Url" not-null="false" sql-type="nvarchar" />
    </property>
    <property name="Orden" type="Int32">
      <column name="Orden" not-null="false" precision="10" scale="0" sql-type="int" />
    </property>
  </class>
</hibernate-mapping>